weather_comp/__init__.py
weather_comp/client.py
weather_comp-0.0.5.dist-info/LICENSE
weather_comp-0.0.5.dist-info/METADATA
weather_comp-0.0.5.dist-info/WHEEL
weather_comp-0.0.5.dist-info/top_level.txt
weather_comp-0.0.5.dist-info/RECORD
